cortix/__init__.py
cortix/docs/Makefile
cortix/docs/build_docs.sh
cortix/docs/conf.py
cortix/docs/contents.rst
cortix/docs/cortix-cover.png
cortix/docs/index.rst
cortix/docs/install.rst
cortix/docs/license.rst
cortix/docs/logo-old.jpg
cortix/docs/logo.jpg
cortix/docs/_templates/globaltoc.html
cortix/docs/examples_rst/examples.rst
cortix/docs/examples_rst/modules.rst
cortix/docs/examples_rst/city_justice_rst/adjudication.rst
cortix/docs/examples_rst/city_justice_rst/arrested.rst
cortix/docs/examples_rst/city_justice_rst/community.rst
cortix/docs/examples_rst/city_justice_rst/jail.rst
cortix/docs/examples_rst/city_justice_rst/modules.rst
cortix/docs/examples_rst/city_justice_rst/parole.rst
cortix/docs/examples_rst/city_justice_rst/prison.rst
cortix/docs/examples_rst/city_justice_rst/probation.rst
cortix/docs/examples_rst/city_justice_rst/run_city_justice.rst
cortix/docs/examples_rst/droplet_swirl_rst/droplet.rst
cortix/docs/examples_rst/droplet_swirl_rst/modules.rst
cortix/docs/examples_rst/droplet_swirl_rst/run_droplet_swirl.rst
cortix/docs/examples_rst/droplet_swirl_rst/vortex.rst
cortix/docs/examples_rst/nbody_rst/body.rst
cortix/docs/examples_rst/nbody_rst/modules.rst
cortix/docs/examples_rst/nbody_rst/run_planets.rst
cortix/docs/src_rst/cortix_main.rst
cortix/docs/src_rst/module.rst
cortix/docs/src_rst/modules.rst
cortix/docs/src_rst/network.rst
cortix/docs/src_rst/node.rst
cortix/docs/src_rst/port.rst
cortix/docs/support_rst/modules.rst
cortix/docs/support_rst/periodictable.rst
cortix/docs/support_rst/phase.rst
cortix/docs/support_rst/phase_new.rst
cortix/docs/support_rst/phase_newest.rst
cortix/docs/support_rst/quantity.rst
cortix/docs/support_rst/specie.rst
cortix/docs/support_rst/species.rst
cortix/docs/support_rst/stream.rst
cortix/docs/support_rst/nuclear_rst/actor.rst
cortix/docs/support_rst/nuclear_rst/fuel_bucket.rst
cortix/docs/support_rst/nuclear_rst/fuel_bundle.rst
cortix/docs/support_rst/nuclear_rst/fuel_segment.rst
cortix-1.1.66.dist-info/LICENSE.txt
cortix-1.1.66.dist-info/METADATA
cortix-1.1.66.dist-info/WHEEL
cortix-1.1.66.dist-info/top_level.txt
cortix-1.1.66.dist-info/RECORD
