Metadata-Version: 2.1
Name: cortix
Version: 1.1.66
Summary: Cortix is a Python library for network dynamics modeling and HPC simulation.
Home-page: https://cortix.org
Author: Cortix Computing
Author-email: valmor_dealmeida@uml.edu
Keywords: simulation,math
Classifier: Programming Language :: Python :: 3
Classifier: License :: OSI Approved :: GNU General Public License v3 (GPLv3)
Classifier: Topic :: Scientific/Engineering :: Mathematics
Classifier: Intended Audience :: Developers
Classifier: Intended Audience :: Education
Classifier: Intended Audience :: End Users/Desktop
Classifier: Intended Audience :: Science/Research
Classifier: Operating System :: MacOS
Classifier: Operating System :: Unix
Classifier: Topic :: Education
Classifier: Topic :: Utilities
Requires-Python: >=3.09
License-File: LICENSE.txt
Requires-Dist: pandas
Requires-Dist: matplotlib
Requires-Dist: numpy
Requires-Dist: scipy
Requires-Dist: pytest
Requires-Dist: graphviz
